puremvc/__init__.py
puremvc/core/Controller.py
puremvc/core/Model.py
puremvc/core/View.py
puremvc/core/__init__.py
puremvc/interfaces/ICommand.py
puremvc/interfaces/IController.py
puremvc/interfaces/IFacade.py
puremvc/interfaces/IMediator.py
puremvc/interfaces/IModel.py
puremvc/interfaces/INotification.py
puremvc/interfaces/INotifier.py
puremvc/interfaces/IObserver.py
puremvc/interfaces/IProxy.py
puremvc/interfaces/IView.py
puremvc/interfaces/__init__.py
puremvc/patterns/__init__.py
puremvc/patterns/command/MacroCommand.py
puremvc/patterns/command/SimpleCommand.py
puremvc/patterns/command/__init__.py
puremvc/patterns/facade/Facade.py
puremvc/patterns/facade/Notifier.py
puremvc/patterns/facade/__init__.py
puremvc/patterns/mediator/Mediator.py
puremvc/patterns/mediator/__init__.py
puremvc/patterns/observer/Notification.py
puremvc/patterns/observer/Observer.py
puremvc/patterns/observer/__init__.py
puremvc/patterns/proxy/Proxy.py
puremvc/patterns/proxy/__init__.py
puremvc-2.0.2.dist-info/licenses/LICENSE
puremvc-2.0.2.dist-info/METADATA
puremvc-2.0.2.dist-info/WHEEL
puremvc-2.0.2.dist-info/top_level.txt
puremvc-2.0.2.dist-info/RECORD
