Metadata-Version: 2.4
Name: PureMVC
Version: 2.0.2
Summary: PureMVC Multicore Framework
Author-email: Saad Shams <saad.shams@puremvc.org>
License-Expression: BSD-3-Clause
Project-URL: Homepage, https://puremvc.org
Project-URL: Source, https://github.com/PureMVC/puremvc-python-multicore-framework
Project-URL: Documentation, https://puremvc.org/puremvc-python-multicore-framework/
Keywords: puremvc,mvc,model,view,controller,patterns
Classifier: Development Status :: 5 - Production/Stable
Classifier: Intended Audience :: Developers
Classifier: Programming Language :: Python :: 3
Classifier: Topic :: Utilities
Requires-Python: >=3.8
License-File: LICENSE
Dynamic: license-file
